{
  "theme": "Light",
  "archetype": "Archetype 4: Swiss & High-Contrast (Fintech Variant)",
  "colors": {
    "background": {
      "default": "#FFFFFF",
      "muted": "#F8F9FA",
      "sidebar": "#F4F5F7"
    },
    "primary": {
      "DEFAULT": "#0A2540",
      "hover": "#051A2E",
      "foreground": "#FFFFFF"
    },
    "accent": {
      "success": "#10B981",
      "successHover": "#059669",
      "successForeground": "#FFFFFF",
      "danger": "#EF4444",
      "dangerHover": "#DC2626"
    },
    "text": {
      "primary": "#0F172A",
      "secondary": "#64748B",
      "tertiary": "#94A3B8"
    },
    "border": {
      "default": "#E2E8F0",
      "light": "#F1F5F9"
    }
  },
  "typography": {
    "headings": {
      "fontFamily": "Outfit, sans-serif",
      "weights": ["500", "600", "700"],
      "tracking": "tracking-tight"
    },
    "body": {
      "fontFamily": "Inter, sans-serif",
      "weights": ["400", "500"]
    },
    "scales": {
      "h1": "text-4xl sm:text-5xl lg:text-6xl font-semibold tracking-tighter text-slate-900",
      "h2": "text-2xl sm:text-3xl lg:text-4xl font-semibold tracking-tight text-slate-900",
      "h3": "text-xl sm:text-2xl font-medium tracking-tight text-slate-800",
      "h4": "text-lg sm:text-xl font-medium text-slate-800",
      "body": "text-base text-slate-600 leading-relaxed",
      "small": "text-sm text-slate-500",
      "overline": "text-xs font-semibold tracking-[0.2em] uppercase text-slate-500"
    }
  },
  "spacing": {
    "section": "py-20 lg:py-32",
    "container": "px-6 lg:px-12 max-w-7xl mx-auto",
    "card": "p-6 sm:p-8"
  },
  "layout": {
    "dashboard": "Bento Grid Protocol (Mode B): grid-cols-1 md:grid-cols-3 lg:grid-cols-4 gap-6",
    "marketing": "Asymmetric Swiss Grid: grid-cols-1 md:grid-cols-12 gap-8 lg:gap-12"
  },
  "components": {
    "cards": "bg-white border border-slate-200 rounded-xl shadow-sm hover:shadow-md transition-shadow duration-200",
    "buttons": {
      "primary": "bg-[#0A2540] hover:bg-[#051A2E] text-white rounded-lg px-6 py-2.5 font-medium transition-colors",
      "success": "bg-emerald-500 hover:bg-emerald-600 text-white rounded-lg px-6 py-2.5 font-medium transition-colors",
      "outline": "border border-slate-200 bg-transparent hover:bg-slate-50 text-slate-900 rounded-lg px-6 py-2.5 font-medium transition-colors"
    },
    "sidebar": "w-64 bg-[#F8F9FA] border-r border-slate-200 h-screen fixed left-0 top-0",
    "header": "h-16 border-b border-slate-200 bg-white/80 backdrop-blur-xl sticky top-0 z-50",
    "inputs": "bg-white border border-slate-200 rounded-lg px-4 py-2 text-slate-900 focus:ring-2 focus:ring-[#0A2540]/20 focus:border-[#0A2540] transition-all",
    "badge": {
      "demo": "bg-slate-100 text-slate-700 border border-slate-200 px-2.5 py-0.5 rounded-full text-xs font-medium",
      "real": "bg-emerald-50 text-emerald-700 border border-emerald-200 px-2.5 py-0.5 rounded-full text-xs font-medium"
    }
  },
  "interactions_and_motion": {
    "hover": "All interactive elements must change state on hover. Buttons darken, cards lift slightly (-translate-y-1).",
    "transitions": "Use 'transition-all duration-200 ease-out' globally for standard UI changes.",
    "page_load": "Staggered fade-up for dashboard widgets and list items."
  },
  "accessibility": {
    "contrast": "Ensure all text against backgrounds meets minimum 4.5:1 ratio (APCA guidelines).",
    "testing": "MUST include 'data-testid' on all interactive and key informational elements (buttons, inputs, toggles, balances, charts)."
  },
  "media_assets": {
    "hero_background": {
      "url": "https://static.prod-images.emergentagent.com/jobs/665453e7-75d6-45f5-8709-92527a0aed60/images/56ce5b489ce823c85513cc281e1843c75566586a51f60abfa5266ff703637928.png",
      "description": "Abstract clean fintech 3D shapes in navy and mint, perfect for landing page hero background (use with opacity/overlay to maintain text contrast)."
    },
    "trading_illustration": {
      "url": "https://static.prod-images.emergentagent.com/jobs/665453e7-75d6-45f5-8709-92527a0aed60/images/f698cd7e90451c627ecc9ab594f2bbd641b6300418a354a584952b726a7f18b2.png",
      "description": "Minimalist 3D isometric financial trading chart trending upward. Use in onboarding or Learn center."
    },
    "onboarding_texture": {
      "url": "https://static.prod-images.emergentagent.com/jobs/665453e7-75d6-45f5-8709-92527a0aed60/images/8416bbb983af3d725369b77c67c3ea95cf1e6b2f4308940c69041dbfbb456aec.png",
      "description": "Soft gradient background for auth pages or onboarding wizard."
    },
    "testimonial_portraits": [
      {
        "url": "https://images.pexels.com/photos/36934779/pexels-photo-36934779.jpeg?auto=compress&cs=tinysrgb&dpr=2&h=650&w=940",
        "description": "Professional user portrait"
      },
      {
        "url": "https://images.unsplash.com/photo-1762522926157-bcc04bf0b10a?crop=entropy&cs=srgb&fm=jpg&ixid=M3w4NjY2NzN8MHwxfHNlYXJjaHwxfHxidXNpbmVzcyUyMHByb2Zlc3Npb25hbCUyMHBvcnRyYWl0JTIwY2xlYW58ZW58MHx8fHwxNzc2NzgxMzM1fDA&ixlib=rb-4.1.0&q=85",
        "description": "Casual professional portrait"
      }
    ],
    "broker_logos": [
      {
        "url": "https://images.pexels.com/photos/9973170/pexels-photo-9973170.jpeg?auto=compress&cs=tinysrgb&dpr=2&h=650&w=940",
        "description": "Partner Broker 1 Logo"
      },
      {
        "url": "https://images.unsplash.com/photo-1764344815160-0e2afc6939a0?crop=entropy&cs=srgb&fm=jpg&ixid=M3w4NjA1NzV8MHwxfHNlYXJjaHwyfHxjb21wYW55JTIwbG9nbyUyMHdoaXRlJTIwYmFja2dyb3VuZHxlbnwwfHx8fDE3NzY3MDgzOTV8MA&ixlib=rb-4.1.0&q=85",
        "description": "Partner Broker 2 Logo"
      }
    ]
  },
  "specific_instructions_to_main_agent": {
    "demo_real_toggle": "Create a highly visible, pill-shaped toggle switch in the main header or top of the sidebar. In Demo mode, show a subtle gray/blue 'Practice' badge. In Real mode, switch accent to soft green 'Live' badge and update dashboard CTAs to point to broker redirect links instead of internal simulator actions.",
    "charts": "Use Recharts or Shadcn charts. Ensure lines and areas use the primary navy or accent green colors. No grid lines on the X/Y axes to maintain the clean Stripe-like look.",
    "tech_stack": "MUST use standard .js extensions (NO TSX). Use standard HTML elements formatted with Tailwind classes for layout structures. For complex interactive elements like the mode toggle or modal popups, use customized Shadcn UI components.",
    "icons": "Use lucide-react (default) with thin stroke-width (1.5) to keep the minimal aesthetic.",
    "testing": "All interactive elements and key text MUST have a 'data-testid' attribute (e.g., data-testid='mode-toggle-switch')."
  }
}